sitejuicer/__init__.py
sitejuicer/__main__.py
sitejuicer/cli.py
sitejuicer/core.py
sitejuicer/py.typed
sitejuicer/ui.py
sitejuicer-0.2.6.dist-info/LICENSE
sitejuicer-0.2.6.dist-info/METADATA
sitejuicer-0.2.6.dist-info/WHEEL
sitejuicer-0.2.6.dist-info/entry_points.txt
sitejuicer-0.2.6.dist-info/top_level.txt
sitejuicer-0.2.6.dist-info/RECORD
