Metadata-Version: 2.2
Name: sitejuicer
Version: 0.2.6
Summary: Convert URLs to markdown using Jina Reader
Home-page: https://github.com/jakerains/sitejuicer
Author: Jake Rains
Author-email: Jake Rains <your-email@example.com>
License: MIT
Project-URL: Homepage, https://github.com/jakerains/sitejuicer
Project-URL: Bug Tracker, https://github.com/jakerains/sitejuicer/issues
Keywords: web scraping,markdown,url,jina,reader,sitejuicer
Classifier: Development Status :: 3 - Alpha
Classifier: Intended Audience :: Developers
Classifier: License :: OSI Approved :: MIT License
Classifier: Programming Language :: Python :: 3
Classifier: Programming Language :: Python :: 3.7
Classifier: Programming Language :: Python :: 3.8
Classifier: Programming Language :: Python :: 3.9
Classifier: Programming Language :: Python :: 3.10
Classifier: Programming Language :: Python :: 3.11
Classifier: Operating System :: OS Independent
Classifier: Operating System :: Microsoft :: Windows
Classifier: Operating System :: MacOS :: MacOS X
Classifier: Operating System :: POSIX :: Linux
Classifier: Topic :: Internet :: WWW/HTTP
Classifier: Topic :: Text Processing :: Markup :: Markdown
Classifier: Topic :: Utilities
Requires-Python: >=3.7
License-File: LICENSE
Requires-Dist: requests>=2.25.0
Requires-Dist: rich>=12.0.0
Requires-Dist: commonmark>=0.9.1
Requires-Dist: typer>=0.7.0
Provides-Extra: dev
Requires-Dist: pytest>=7.0.0; extra == "dev"
Requires-Dist: black>=22.0.0; extra == "dev"
Requires-Dist: isort>=5.0.0; extra == "dev"
Requires-Dist: mypy>=0.9.0; extra == "dev"
Requires-Dist: flake8>=5.0.0; extra == "dev"
Provides-Extra: ui
Requires-Dist: textual>=0.11.0; extra == "ui"
Provides-Extra: full
Requires-Dist: textual>=0.11.0; extra == "full"
Dynamic: author
Dynamic: home-page
Dynamic: requires-python
